LICENSE.md
README.md
setup.py
cycleenrichr/__init__.py
cycleenrichr/enrichment.py
cycleenrichr/enrichr.py
cycleenrichr/load.py
cycleenrichr.egg-info/PKG-INFO
cycleenrichr.egg-info/SOURCES.txt
cycleenrichr.egg-info/dependency_links.txt
cycleenrichr.egg-info/requires.txt
cycleenrichr.egg-info/top_level.txt
cycleenrichr/data/KEGG_2021_Human
cycleenrichr/data/config.json